eo_kit-0.1.3.dist-info/METADATA
eo_kit-0.1.3.dist-info/WHEEL
eo_kit-0.1.3.dist-info/license_files/LICENSE
EOkit/EOkit/__init__.py
EOkit/EOkit/ffi.py
EOkit/gaussian_processes.py
EOkit/__init__.py
EOkit/smoothers/whittaker.py
EOkit/smoothers/__init__.py
EOkit/smoothers/sav_golay.py
EOkit/array_utils.py
EOkit/EOkit/__init__.py
EOkit/EOkit/ffi.py
EOkit/EOkit/native.so
eo_kit-0.1.3.dist-info/RECORD
