Metadata-Version: 2.1
Name: eo-kit
Version: 0.1.3
Classifier: License :: OSI Approved :: MIT License
Classifier: Programming Language :: Rust
Classifier: Programming Language :: Python :: Implementation :: CPython
Classifier: Programming Language :: Python :: Implementation :: PyPy
Classifier: Topic :: Scientific/Engineering
Classifier: Intended Audience :: Science/Research
Requires-Dist: cffi
Requires-Dist: numpy
License-File: LICENSE
Summary: A multithreaded library for efficient Earth observation algorithms.
Author: Andrew Bowell
Requires-Python: >=3.6
Project-URL: repository, https://github.com/AnBowell/eo-kit
Project-URL: documentation, https://eo-kit.readthedocs.io/en/latest/
